prosodia/__init__.py
prosodia/py.typed
prosodia/base/__init__.py
prosodia/base/augmentedbnf/__init__.py
prosodia/base/augmentedbnf/_intermediate_parser.py
prosodia/base/augmentedbnf/_intermediate_text.py
prosodia/base/augmentedbnf/_intermediate_transform.py
prosodia/base/augmentedbnf/_parser.py
prosodia/base/augmentedbnf/_text.py
prosodia/base/augmentedbnf/_transform.py
prosodia/base/augmentedbnf/_transform_helpers.py
prosodia/base/augmentedbnf/_transform_terminals.py
prosodia/base/augmentedbnf/intermediate_text.grammar
prosodia/base/augmentedbnf/text.grammar
prosodia/base/augmentedbnf/_freebies/__init__.py
prosodia/base/augmentedbnf/_freebies/text.grammar
prosodia/base/augmentedbnf/_freebies/text.py
prosodia/base/bnf/__init__.py
prosodia/base/bnf/_grammar.py
prosodia/base/bnf/_parser.py
prosodia/base/bnf/_text.py
prosodia/base/bnf/_transform.py
prosodia/base/bnf/text.grammar
prosodia/base/bnfrange/__init__.py
prosodia/base/bnfrange/_grammar.py
prosodia/base/bnfrange/_parser.py
prosodia/base/bnfrange/_text.py
prosodia/base/bnfrange/_transform.py
prosodia/base/bnfrange/text.grammar
prosodia/base/bnfrange/example/__init__.py
prosodia/base/bnfrange/example/_grammar.py
prosodia/base/bnfrange/example/_text.py
prosodia/base/bnfrange/example/_transform.py
prosodia/base/bnfrange/example/text.grammar
prosodia/base/bnfrepeat/__init__.py
prosodia/base/bnfrepeat/_grammar.py
prosodia/base/bnfrepeat/_parser.py
prosodia/base/bnfrepeat/_text.py
prosodia/base/bnfrepeat/_transform.py
prosodia/base/bnfrepeat/text.grammar
prosodia/base/bnfrepeat/example/__init__.py
prosodia/base/bnfrepeat/example/_grammar.py
prosodia/base/bnfrepeat/example/_text.py
prosodia/base/bnfrepeat/example/_transform.py
prosodia/base/bnfrepeat/example/text.grammar
prosodia/core/__init__.py
prosodia/core/grammar.py
prosodia/core/resolvable.py
prosodia/core/transform.py
prosodia/core/tree.py
prosodia/validation/__init__.py
prosodia/validation/group_types.py
prosodia/validation/switches.py
prosodia-0.5.3.dist-info/LICENSE
prosodia-0.5.3.dist-info/METADATA
prosodia-0.5.3.dist-info/WHEEL
prosodia-0.5.3.dist-info/top_level.txt
prosodia-0.5.3.dist-info/RECORD
