Metadata-Version: 2.1
Name: prosodia
Version: 0.5.3
Summary: UNKNOWN
Home-page: UNKNOWN
Author: macbeth322
Author-email: chrisp533@gmail.com
License: UNKNOWN
Platform: UNKNOWN
Requires-Dist: typing
Provides-Extra: test
Requires-Dist: pytest-cov ; extra == 'test'
Requires-Dist: pytest ; extra == 'test'
